newscraping/__init__.py
newscraping/application/scraping.py
newscraping/infrastructure/infra.py
newscraping/settings/base.py
newscraping-0.1.2.dist-info/entry_points.txt
newscraping-0.1.2.dist-info/WHEEL
newscraping-0.1.2.dist-info/METADATA
newscraping-0.1.2.dist-info/RECORD
