Metadata-Version: 2.1
Name: newscraping
Version: 0.1.2
Summary: Web scraping of financial headlines
Home-page: https://gitlab.com/financial-sentiment/newscraping
License: MIT
Keywords: webscraping,news
Author: Jerome Blin
Requires-Python: >=3.8,<4.0
Classifier: License :: OSI Approved :: MIT License
Classifier: Programming Language :: Python :: 3
Classifier: Programming Language :: Python :: 3.8
Classifier: Programming Language :: Python :: 3.9
Requires-Dist: beautifulsoup4 (>=4.9.3,<5.0.0)
Requires-Dist: pandas (>=1.2.0,<2.0.0)
Requires-Dist: requests (>=2.25.1,<3.0.0)
Project-URL: Documentation, https://newscraping.readthedocs.io/en/latest/
Project-URL: Repository, https://gitlab.com/financial-sentiment/newscraping
